odoo/addons/remote_report_to_printer/README.rst
odoo/addons/remote_report_to_printer/__init__.py
odoo/addons/remote_report_to_printer/__manifest__.py
odoo/addons/remote_report_to_printer/data/printing_data.xml
odoo/addons/remote_report_to_printer/i18n/es.po
odoo/addons/remote_report_to_printer/i18n/remote_report_to_printer.pot
odoo/addons/remote_report_to_printer/models/__init__.py
odoo/addons/remote_report_to_printer/models/ir_actions_report.py
odoo/addons/remote_report_to_printer/models/printing_action.py
odoo/addons/remote_report_to_printer/models/printing_printer.py
odoo/addons/remote_report_to_printer/models/res_remote.py
odoo/addons/remote_report_to_printer/models/res_remote_printer.py
odoo/addons/remote_report_to_printer/readme/CONTRIBUTORS.rst
odoo/addons/remote_report_to_printer/readme/DESCRIPTION.rst
odoo/addons/remote_report_to_printer/readme/USAGE.rst
odoo/addons/remote_report_to_printer/security/ir.model.access.csv
odoo/addons/remote_report_to_printer/static/description/icon.png
odoo/addons/remote_report_to_printer/static/description/index.html
odoo/addons/remote_report_to_printer/tests/__init__.py
odoo/addons/remote_report_to_printer/tests/test_printer.py
odoo/addons/remote_report_to_printer/tests/test_remote_printer.py
odoo/addons/remote_report_to_printer/views/printing_printer.xml
odoo/addons/remote_report_to_printer/views/res_remote_printer_views.xml
odoo/addons/remote_report_to_printer/views/res_remote_views.xml
odoo13_addon_remote_report_to_printer-13.0.1.1.0.dist-info/METADATA
odoo13_addon_remote_report_to_printer-13.0.1.1.0.dist-info/WHEEL
odoo13_addon_remote_report_to_printer-13.0.1.1.0.dist-info/top_level.txt
odoo13_addon_remote_report_to_printer-13.0.1.1.0.dist-info/RECORD
