Metadata-Version: 2.1
Name: odoo13-addon-remote-report-to-printer
Version: 13.0.1.1.0
Summary: Report to printer on remotes
Home-page: http://www.github.com/OCA/report-print-send
Author: Creu Blanca, Odoo Community Association (OCA)
Author-email: support@odoo-community.org
License: AGPL-3
Platform: UNKNOWN
Classifier: Programming Language :: Python
Classifier: Framework :: Odoo
Classifier: Framework :: Odoo :: 13.0
Classifier: License :: OSI Approved :: GNU Affero General Public License v3
Requires-Python: >=3.5
Requires-Dist: odoo13-addon-base-remote
Requires-Dist: odoo13-addon-base-report-to-printer
Requires-Dist: odoo (<13.1dev,>=13.0a)
